data_harvesting/__init__.py
data_harvesting/aggregator.py
data_harvesting/cli/__init__.py
data_harvesting/cli/aggregator.py
data_harvesting/cli/cli.py
data_harvesting/cli/converter.py
data_harvesting/cli/cron/__init__.py
data_harvesting/cli/cron/cron
data_harvesting/cli/cron/setup.py
data_harvesting/cli/datapipeline.py
data_harvesting/cli/harvesters.py
data_harvesting/cli/indexer.py
data_harvesting/cli/stats.py
data_harvesting/cli/util.py
data_harvesting/configs/config.yaml
data_harvesting/data_enrichment/SPARQL-update.rq
data_harvesting/data_enrichment/generate_queries/add_organizations.py
data_harvesting/data_enrichment/generate_queries/add_organizations.rd
data_harvesting/data_enrichment/generate_queries/multiple_org_names.json
data_harvesting/data_enrichment/generate_queries/remove_redundant_single_org.py
data_harvesting/data_enrichment/generate_queries/remove_redundant_single_org.rd
data_harvesting/data_enrichment/generate_queries/single_org_names.json
data_harvesting/data_enrichment/schema_infer_org.rd
data_harvesting/data_enrichment/schema_infer_org_id.rd
data_harvesting/data_enrichment/schema_infer_organization.rd
data_harvesting/data_enrichment/schema_infer_person.rd
data_harvesting/data_enrichment/schema_set_org_iri.rd
data_harvesting/data_model.py
data_harvesting/external_schema/README.md
data_harvesting/external_schema/codemeta.jsonld
data_harvesting/external_schema/context_cache.yaml
data_harvesting/external_schema/schema_org.jsonld
data_harvesting/external_schema/schema_org_shacl.jsonld
data_harvesting/harvester/__init__.py
data_harvesting/harvester/base.py
data_harvesting/harvester/datacite.py
data_harvesting/harvester/feed.py
data_harvesting/harvester/git.py
data_harvesting/harvester/gitlabs.json
data_harvesting/harvester/indico.py
data_harvesting/harvester/oaipmh/__init__.py
data_harvesting/harvester/oaipmh/constants.py
data_harvesting/harvester/oaipmh/convert_harvest.py
data_harvesting/harvester/oaipmh/jsonldoutput.py
data_harvesting-2.0.0.dist-info/LICENSES/CC0-1.0.txt
data_harvesting-2.0.0.dist-info/LICENSES/MIT.txt
data_harvesting-2.0.0.dist-info/METADATA
data_harvesting-2.0.0.dist-info/WHEEL
data_harvesting-2.0.0.dist-info/entry_points.txt
data_harvesting-2.0.0.dist-info/RECORD
