Metadata-Version: 2.1
Name: data-harvesting
Version: 2.0.0
Summary: Set of tools to harvest, process and uplift (meta)data from metadata providers within the Helmholtz association to be included in the Helmholtz Knowledge Graph (Helmholtz-KG).
Home-page: https://codebase.helmholtz.cloud/hmc/hmc-public/unhide/data_harvesting
License: MIT
Keywords: unhide,Helmholtz association,data mining,HMC,metadata,data publications,software publication,RSE,FAIR,linked data,knowledge graph,json-ld,schema.org,restruct
Author: Jens Bröder
Author-email: j.broeder@fz-juelich.de
Maintainer: Jens Bröder
Maintainer-email: j.broeder@fz-juelich.de
Requires-Python: >=3.9,<4.0
Classifier: Development Status :: 4 - Beta
Classifier: Intended Audience :: Information Technology
Classifier: Intended Audience :: Science/Research
Classifier: License :: OSI Approved :: MIT License
Classifier: Natural Language :: English
Classifier: Operating System :: MacOS :: MacOS X
Classifier: Operating System :: POSIX :: Linux
Classifier: Programming Language :: Python
Classifier: Programming Language :: Python :: 3
Classifier: Programming Language :: Python :: 3.9
Classifier: Programming Language :: Python :: 3.10
Classifier: Programming Language :: Python :: 3.11
Classifier: Programming Language :: Python :: 3.12
Classifier: Topic :: Database
Classifier: Topic :: Education
Classifier: Topic :: Scientific/Engineering
Classifier: Topic :: Scientific/Engineering :: Information Analysis
Classifier: Topic :: Scientific/Engineering :: Visualization
Classifier: Topic :: Text Processing
Classifier: Typing :: Typed
Requires-Dist: SPARQLWrapper (>=2.0.0,<3.0.0)
Requires-Dist: advertools (>=0.13.2,<0.14.0)
Requires-Dist: atoma (>=0.0.17,<0.0.18)
Requires-Dist: extruct (>=0.16.0,<0.17.0)
Requires-Dist: jsondiff (>=2.0.0,<3.0.0)
Requires-Dist: lxml (<5.0.0)
Requires-Dist: oaiharvest (>=3.0.0,<4.0.0)
Requires-Dist: pathos (>=0.3.0,<0.4.0)
Requires-Dist: prefect (>=2.16.9,<3.0.0)
Requires-Dist: progressbar2 (>=4.4.2,<5.0.0)
Requires-Dist: pydantic (>=2.3.0,<3.0.0)
Requires-Dist: pydantic-settings (>=2.2.1,<3.0.0)
Requires-Dist: pygit2 (>=1.15.0,<2.0.0)
Requires-Dist: pyld (>=2.0.3,<3.0.0)
Requires-Dist: pyoai (==2.5.0)
Requires-Dist: pyshacl (>=0.25.0,<0.26.0)
Requires-Dist: python-crontab (>=3.0.0,<4.0.0)
Requires-Dist: python-dateutil (>=2.8.2,<3.0.0)
Requires-Dist: rdflib (>=6.2.0,<7.0.0)
Requires-Dist: requests (>=2.28.1,<3.0.0)
Requires-Dist: shapely (>=2.0.1,<3.0.0)
Requires-Dist: typer[all] (>=0.12.1,<0.13.0)
Requires-Dist: vcrpy (>=6.0.1,<7.0.0)
Requires-Dist: wrapt (>=1.15.0,<2.0.0)
Project-URL: Repository, https://codebase.helmholtz.cloud/hmc/hmc-public/unhide/data_harvesting.git
